{"name":"build-javascript","namedChunkGroups":{"app":{"name":"app","assets":[{"name":"webpack-runtime-b0a3d7270e57269af223.js","size":4925},{"name":"framework-285a110df369ca8e03e8.js","size":140773},{"name":"app-61cfe4b01d99fe6cebd5.js","size":68156}],"filteredAssets":0,"assetsSize":213854,"filteredAuxiliaryAssets":3,"auxiliaryAssetsSize":613394},"component---src-pages-404-tsx":{"name":"component---src-pages-404-tsx","assets":[{"name":"component---src-pages-404-tsx-0fafe188ad7b785c5cf0.js","size":778}],"filteredAssets":0,"assetsSize":778,"filteredAuxiliaryAssets":1,"auxiliaryAssetsSize":1912},"component---src-pages-index-tsx":{"name":"component---src-pages-index-tsx","assets":[{"name":"styles.d1b40e3a67537a8415bb.css","size":143983},{"name":"component---src-pages-index-tsx-2ea667c814f72e3eefb6.js","size":61710}],"filteredAssets":0,"assetsSize":205693,"filteredAuxiliaryAssets":20,"auxiliaryAssetsSize":389897}},"assetsByChunkName":{"app":["webpack-runtime-b0a3d7270e57269af223.js","framework-285a110df369ca8e03e8.js","app-61cfe4b01d99fe6cebd5.js"],"component---src-pages-404-tsx":["component---src-pages-404-tsx-0fafe188ad7b785c5cf0.js"],"component---src-pages-index-tsx":["styles.d1b40e3a67537a8415bb.css","component---src-pages-index-tsx-2ea667c814f72e3eefb6.js"]},"childAssetsByChunkName":{}}